awesom_sitemap_parser/__about__.py
awesom_sitemap_parser/__init__.py
awesom_sitemap_parser/exceptions.py
awesom_sitemap_parser/fetch_parse.py
awesom_sitemap_parser/helpers.py
awesom_sitemap_parser/log.py
awesom_sitemap_parser/objects/__init__.py
awesom_sitemap_parser/objects/page.py
awesom_sitemap_parser/objects/sitemap.py
awesom_sitemap_parser/tree.py
awesom_sitemap_parser/web_client/__init__.py
awesom_sitemap_parser/web_client/abstract_client.py
awesom_sitemap_parser/web_client/requests_client.py
awesom_sitemap_parser/web_client/zyte_client.py
awesom_sitemap_parser-0.1.0.dist-info/LICENSE
awesom_sitemap_parser-0.1.0.dist-info/METADATA
awesom_sitemap_parser-0.1.0.dist-info/WHEEL
awesom_sitemap_parser-0.1.0.dist-info/RECORD
